rftools/__init__.py
rftools/misc.py
rftools/network.py
rftools/noise.py
rftools/parameters.py
rftools/tlines.py
rftools/util.py
rftools-0.0.3.data/scripts/50ohm-line
rftools-0.0.3.data/scripts/cwaveguide
rftools-0.0.3.data/scripts/noisetemp
rftools-0.0.3.data/scripts/temp-cw
rftools-0.0.3.data/scripts/temp-rj
rftools-0.0.3.data/scripts/waveguide
rftools-0.0.3.data/scripts/waveguide-att
rftools-0.0.3.dist-info/LICENSE.md
rftools-0.0.3.dist-info/METADATA
rftools-0.0.3.dist-info/WHEEL
rftools-0.0.3.dist-info/top_level.txt
rftools-0.0.3.dist-info/RECORD
