Metadata-Version: 2.1
Name: rftools
Version: 0.0.3
Summary: Tools to design RF components and networks.
Home-page: https://github.com/garrettj403/RF-tools/
Author: John Garrett
Author-email: garrettj403@gmail.com
License: MIT
Project-URL: Changelog, https://github.com/garrettj403/RF-tools/blob/master/CHANGES.md
Project-URL: Issue Tracker, https://github.com/garrettj403/RF-tools/issues
Keywords: RF engineering,Microwave engineering,Electrical engineering,RF components,Touchstone,HFSS
Platform: any
Classifier: Intended Audience :: Science/Research
Classifier: License :: OSI Approved :: MIT License
Classifier: Natural Language :: English
Classifier: Programming Language :: Python :: 3.5
Classifier: Programming Language :: Python :: 3.6
Classifier: Programming Language :: Python :: 3.7
Classifier: Topic :: Scientific/Engineering :: Physics
Requires-Dist: matplotlib
Requires-Dist: numpy
Requires-Dist: scipy
Provides-Extra: testing
Requires-Dist: pytest ; extra == 'testing'
